system_shutdown_timer/__init__.py
system_shutdown_timer/timer.py
system_shutdown_timer-0.1.1.dist-info/LICENSE
system_shutdown_timer-0.1.1.dist-info/METADATA
system_shutdown_timer-0.1.1.dist-info/WHEEL
system_shutdown_timer-0.1.1.dist-info/entry_points.txt
system_shutdown_timer-0.1.1.dist-info/top_level.txt
system_shutdown_timer-0.1.1.dist-info/RECORD
